ab_client/token_issuer_store/__init__.py
ab_client/token_issuer_store/clients/__init__.py
ab_client/token_issuer_store/clients/async_client.py
ab_client/token_issuer_store/clients/sync_client.py
ab_client/token_issuer_store/exceptions/__init__.py
ab_client/token_issuer_store/exceptions/http_exception.py
ab_client/token_issuer_store/models/BrowserlessService_Input.py
ab_client/token_issuer_store/models/BrowserlessService_Output.py
ab_client/token_issuer_store/models/CDPGUIService.py
ab_client/token_issuer_store/models/CreateTokenIssuerRequest.py
ab_client/token_issuer_store/models/HTTPValidationError.py
ab_client/token_issuer_store/models/ImpersonationOAuth2Flow_Input.py
ab_client/token_issuer_store/models/ImpersonationOAuth2Flow_Output.py
ab_client/token_issuer_store/models/Impersonator.py
ab_client/token_issuer_store/models/ImpersonatorTool.py
ab_client/token_issuer_store/models/ManagedTokenIssuer.py
ab_client/token_issuer_store/models/OAuth2TokenIssuer_Input.py
ab_client/token_issuer_store/models/OAuth2TokenIssuer_Output.py
ab_client/token_issuer_store/models/OIDCConfig.py
ab_client/token_issuer_store/models/Oauth2Client.py
ab_client/token_issuer_store/models/Oauth2ClientType.py
ab_client/token_issuer_store/models/Oauth2Flow.py
ab_client/token_issuer_store/models/Oauth2FlowType.py
ab_client/token_issuer_store/models/PKCEOAuth2Client.py
ab_client/token_issuer_store/models/PKCEOAuth2TokenIssuer_Input.py
ab_client/token_issuer_store/models/PKCEOAuth2TokenIssuer_Output.py
ab_client/token_issuer_store/models/PlaywrightCDPBrowserlessImpersonator_Input.py
ab_client/token_issuer_store/models/PlaywrightCDPBrowserlessImpersonator_Output.py
ab_client/token_issuer_store/models/PlaywrightCDPImpersonator.py
ab_client/token_issuer_store/models/PlaywrightImpersonator.py
ab_client/token_issuer_store/models/StandardOAuth2Client.py
ab_client/token_issuer_store/models/TemplateImpersonator.py
ab_client/token_issuer_store/models/TemplateOAuth2Flow.py
ab_client_token_issuer_store-1.1.1.dist-info/METADATA
ab_client_token_issuer_store-1.1.1.dist-info/WHEEL
ab_client_token_issuer_store-1.1.1.dist-info/licenses/LICENSE
ab_client_token_issuer_store-1.1.1.dist-info/RECORD
