Metadata-Version: 2.4
Name: ab-client-token-issuer-store
Version: 1.1.1
Summary: A client library for accessing FastAPI
License-File: LICENSE
Requires-Python: <4,>=3.9
Requires-Dist: httpx<0.29.0,>=0.23.0
Requires-Dist: pydantic>=2.11.9
